django_politico_fake_news-1.0.6.dist-info/METADATA
django_politico_fake_news-1.0.6.dist-info/RECORD
django_politico_fake_news-1.0.6.dist-info/WHEEL
django_politico_fake_news-1.0.6.dist-info/top_level.txt
fakenews/__init__.py
fakenews/admin.py
fakenews/apps.py
fakenews/authentication.py
fakenews/celery.py
fakenews/conf.py
fakenews/exceptions.py
fakenews/signals.py
fakenews/urls.py
fakenews/management/__init__.py
fakenews/management/commands/__init__.py
fakenews/management/commands/bake.py
fakenews/management/commands/bake_api.py
fakenews/management/commands/bake_data_feed.py
fakenews/management/commands/bake_data_post.py
fakenews/management/commands/bake_data_tag.py
fakenews/management/commands/bake_data_type.py
fakenews/management/commands/bake_pages.py
fakenews/management/commands/bake_template_post.py
fakenews/management/commands/bake_web_context.py
fakenews/management/commands/fakenews_bake.py
fakenews/management/commands/fakenews_bake_api.py
fakenews/management/commands/fakenews_bake_data_feed.py
fakenews/management/commands/fakenews_bake_data_post.py
fakenews/management/commands/fakenews_bake_data_tag.py
fakenews/management/commands/fakenews_bake_data_type.py
fakenews/management/commands/fakenews_bake_pages.py
fakenews/management/commands/fakenews_bake_template_post.py
fakenews/management/commands/fakenews_bake_web_context.py
fakenews/migrations/0001_initial.py
fakenews/migrations/0002_auto_20180813_1949.py
fakenews/migrations/0003_auto_20180813_2017.py
fakenews/migrations/0004_auto_20180813_2057.py
fakenews/migrations/0005_auto_20180813_2058.py
fakenews/migrations/0006_auto_20181001_1625.py
fakenews/migrations/__init__.py
fakenews/models/__init__.py
fakenews/models/claim.py
fakenews/models/disinformation_type.py
fakenews/models/fact_check.py
fakenews/models/share.py
fakenews/models/source.py
fakenews/serializers/__init__.py
fakenews/serializers/claim.py
fakenews/serializers/disinformation_type.py
fakenews/serializers/fact_check.py
fakenews/serializers/share.py
fakenews/serializers/slate.py
fakenews/serializers/source.py
fakenews/serializers/tag.py
fakenews/serializers/user.py
fakenews/static/.DS_Store
