Metadata-Version: 2.1
Name: django-politico-fake-news
Version: 1.0.6
Summary: Database of fake news.
Home-page: https://github.com/The-Politico/django-politico-fake-news
Author: POLITICO interactive news
Author-email: interactives@politico.com
License: MIT
Platform: UNKNOWN
Classifier: Development Status :: 3 - Alpha
Classifier: Framework :: Django
Classifier: Framework :: Django :: 2.0
Classifier: Intended Audience :: Developers
Classifier: Intended Audience :: Information Technology
Classifier: License :: OSI Approved :: MIT License
Classifier: Operating System :: OS Independent
Classifier: Programming Language :: Python :: 3
Classifier: Programming Language :: Python :: 3.5
Classifier: Programming Language :: Python :: 3.6
Classifier: Topic :: Internet :: WWW/HTTP
Requires-Dist: django-taggit
Requires-Dist: django-taggit-serializer
Requires-Dist: djangorestframework
Requires-Dist: savepagenow
Provides-Extra: test
Requires-Dist: pytest; extra == 'test'
